regfans/__init__.py
regfans/circuits.py
regfans/fan.py
regfans/util.py
regfans/vectorconfig.py
regfans-0.0.4.dist-info/licenses/LICENSE
regfans-0.0.4.dist-info/METADATA
regfans-0.0.4.dist-info/WHEEL
regfans-0.0.4.dist-info/top_level.txt
regfans-0.0.4.dist-info/RECORD
