Metadata-Version: 2.4
Name: regfans
Version: 0.0.4
Summary: Regular fans of vector configurations
Author: Nate MacFadden
License-Expression: GPL-3.0-or-later
Project-URL: Repository, https://github.com/natemacfadden/regfans
Classifier: Programming Language :: Python :: 3
Classifier: Programming Language :: Python :: 3.9
Requires-Python: <3.14,>=3.9
License-File: LICENSE
Requires-Dist: python-flint
Requires-Dist: ortools
Requires-Dist: networkx
Requires-Dist: numpy
Requires-Dist: scipy
Requires-Dist: triangulumancer
Provides-Extra: test
Requires-Dist: pplpy; extra == "test"
Requires-Dist: pytest; extra == "test"
Dynamic: license-file
